{
  "병명": "대동맥판막 질환",
  "증상": {
    "Amc": null,
    "Snu": null,
    "Kdca": null,
    "Final": "대동맥 판막 질환을 가진 일부 사람들은 수년 동안 증상을 느끼지 못할 수 있습니다. 대동맥 판막 질환의 징후와 증상은 다음과 같습니다: - 심장에서 나는 쉭쉭거리는 소리(심잡음) - 가슴 통증 또는 압박감 - 어지러움 - 실신 - 활동 후 피로감 또는 활동 능력 감소 - 불규칙한 심장 박동 - 숨 가쁨, 특히 격렬한 활동 중이나 누워 있을 때 - 식욕 부진(주로 대동맥 판막 협착증이 있는 어린이에게서) - 체중 증가 부족(주로 대동맥 판막 협착증이 있는 어린이에게서) 이러한 증상이 나타날 경우 적절한 진단과 치료를 위해 의료 전문가와 상담하는 것이 중요합니다.",
    "1200": null
  },
  "정의": {
    "Amc": null,
    "Snu": null,
    "Kdca": null,
    "Final": null,
    "1200": null
  },
  "원인": {
    "Amc": null,
    "Snu": null,
    "Kdca": null,
    "Final": null,
    "1200": null
  },
  "진단": {
    "Amc": null,
    "Snu": null,
    "Kdca": null,
    "Final": null,
    "1200": null
  },
  "치료": {
    "Amc": null,
    "Snu": null,
    "Kdca": null,
    "Final": null,
    "1200": null
  },
  "진료과": {
    "Amc": null,
    "Snu": null,
    "Kdca": null,
    "Final": null,
    "1200": null
  }
}