{
  "병명": "목 통증",
  "증상": {
    "Amc": null,
    "Snu": null,
    "Kdca": null,
    "Final": "증상에는 다음과 같은 것들이 포함됩니다: 장시간 동안 머리를 한 곳에 고정하고 있을 때, 예를 들어 운전하거나 컴퓨터 작업을 할 때 통증이 악화됨, 근육 긴장과 경련, 머리 움직임의 제한, 두통.",
    "1200": null
  },
  "정의": {
    "Amc": null,
    "Snu": null,
    "Kdca": null,
    "Final": null,
    "1200": null
  },
  "원인": {
    "Amc": null,
    "Snu": null,
    "Kdca": null,
    "Final": null,
    "1200": null
  },
  "진단": {
    "Amc": null,
    "Snu": null,
    "Kdca": null,
    "Final": null,
    "1200": null
  },
  "치료": {
    "Amc": null,
    "Snu": null,
    "Kdca": null,
    "Final": null,
    "1200": null
  },
  "진료과": {
    "Amc": null,
    "Snu": null,
    "Kdca": null,
    "Final": null,
    "1200": null
  }
}