{
  "병명": "복잡성 애도",
  "증상": {
    "Amc": null,
    "Snu": null,
    "Kdca": null,
    "Final": "상실 후 첫 몇 달 동안, 정상적인 슬픔의 징후와 증상은 복잡한 슬픔의 징후와 증상과 비슷합니다. 그러나 정상적인 슬픔의 증상은 시간이 지나면서 점차 사라지는 반면, 복잡한 슬픔의 증상은 지속되거나 악화됩니다. 복잡한 슬픔은 치유를 방해하는 지속적이고 고조된 애도의 상태와 같습니다. 복잡한 슬픔의 징후와 증상은 다음과 같습니다: - 사랑하는 사람의 상실에 대한 강렬한 슬픔, 고통, 그리고 끊임없는 생각 - 사랑하는 사람의 죽음 외에는 거의 다른 것에 집중하지 못함 - 사랑하는 사람을 떠올리게 하는 것에 대한 극도의 집중 또는 지나친 회피 - 사망한 사람에 대한 강렬하고 지속적인 그리움 - 죽음을 받아들이기 어려움 - 무감각하거나 분리된 느낌 - 상실에 대한 씁쓸함 - 삶이 의미나 목적이 없다고 느낌 - 타인에 대한 신뢰 부족 - 삶을 즐기거나 사랑하는 사람과의 긍정적인 경험을 회상하는 데 어려움 복잡한 슬픔은 또한 다음과 같은 경우에도 나타날 수 있습니다: - 일상적인 활동을 수행하는 데 어려움을 겪음",
    "1200": null
  },
  "정의": {
    "Amc": null,
    "Snu": null,
    "Kdca": null,
    "Final": null,
    "1200": null
  },
  "원인": {
    "Amc": null,
    "Snu": null,
    "Kdca": null,
    "Final": null,
    "1200": null
  },
  "진단": {
    "Amc": null,
    "Snu": null,
    "Kdca": null,
    "Final": null,
    "1200": null
  },
  "치료": {
    "Amc": null,
    "Snu": null,
    "Kdca": null,
    "Final": null,
    "1200": null
  },
  "진료과": {
    "Amc": null,
    "Snu": null,
    "Kdca": null,
    "Final": null,
    "1200": null
  }
}