{
  "병명": "연성하감",
  "증상": {
    "Amc": null,
    "Snu": null,
    "Kdca": "전형적인 성기 궤양은 경계가 뚜렷하며 지름은 2cm의 크기를 갖습니다. 궤양은 남성의 경우 음경의 포피, 음경귀두관, 음경 등에, 여성의 경우 음순, 질입구, 항문주위 등에 주로 생기게 됩니다. 성기 궤양이 나타난 이후 1~2주가 지나면 종종 심한 통증을 동반한 서혜부 림프절염이 발생하는데, 남성은 1/3의 환자에서 발생하며 여성은 더 낮은 빈도로 나타납니다. 적절한 치료를 하지 않으면 침범된 림프절이 액화과정을 거쳐 부보(buboes)라고 부르는 병변을 형성하고 이때 저절로 터져서 농이 흘러나오게 됩니다.",
    "Final": null,
    "1200": null
  },
  "정의": {
    "Amc": null,
    "Snu": null,
    "Kdca": "[헤모필루스 두크레이균(Haemophilus ducreyi) 감염에 의한 성기나 회음부의 통증성 궤양성 질환]",
    "Final": null,
    "1200": null
  },
  "원인": {
    "Amc": null,
    "Snu": null,
    "Kdca": "성접촉에 의해 헤모필루스 두크레이균 (Haemophilus ducreyi)에 감염되면 4일~10일의 잠복기를 거친 후 성기의 붉은 구진에서 시작하여 빠르게 농포로 발전하는 병변이 생기고, 농포가 터져 통증성 궤양을 형성하게 됩니다. 이 궤양이 화농성 분비물이 있고 유연하므로 연성하감이라고 부르게 된 것입니다.",
    "Final": null,
    "1200": null
  },
  "진단": {
    "Amc": null,
    "Snu": null,
    "Kdca": "진단은 환자 병변의 분비물 등에서 헤모필루스 두크레이균을 분리해서 하게 되며, 궤양이나 국소림프절의 농을 도말염색 및 배양하여 검사합니다. 그람염색이나 김자액(Giemsa)염색에서는 닫혀진 안전핀 모양의 균이 쇠사슬 형태로 마치 고기떼처럼 보이는 것을 관찰할 수 있으나 검사의 특이도는 낮은 편입니다. 배양검사는 검사의 특이도는 높으나 특수 배지를 이용하여 시행해야 합니다.  병리조직검사에서는 괴사층, 중간층, 심층부의 세 층으로 이루어진 전형적인 소견을 관찰 할 수 있으면 진단에 도움이 될 수 있습니다. 괴사층은 섬유소와 다형핵백혈구, 괴사조직 등으로 구성되어 있고, 중간층은 육아조직과 새로운 혈관 형성, 내피성 증식을 보이며, 심층부는 형질세포와 림프구의 심한 침착을 보입니다.",
    "Final": null,
    "1200": null
  },
  "치료": {
    "Amc": null,
    "Snu": null,
    "Kdca": "연성하감의 치료는 항생제를 사용하게 되는데, 아지스로마이신 1g을 1회 먹거나, 세프트리악손 250mg을 1회 근육주사로 맞게 됩니다. 심한 경우 궤양부위를 수술로 제거하기도 합니다. 1회 요법이 순응도가 좋아서 주로 사용되고 있지만, 아지스로마이신이나 세프트리악손이 없거나 사용할 수 없을 때는 고식적 요법으로 시프로플록사신 500mg을 하루 2회씩 3일간 먹거나, 에리스로마이신 500mg을 하루 4회씩 일주일간 먹게 됩니다.",
    "Final": null,
    "1200": null
  },
  "진료과": {
    "Amc": null,
    "Snu": null,
    "Kdca": null,
    "Final": null,
    "1200": null
  }
}