{
  "병명": "연축성발성장애",
  "증상": {
    "Amc": null,
    "Snu": "쥐어짜는 듯한 힘이 들어가는 음성, 말을 할때 음성이 단절되고 떨리면서 말을 이어나가기 어려움, 불규칙하게 떨리는 음성 등의 증상이 나타난다.",
    "Kdca": null,
    "Final": null,
    "1200": null
  },
  "정의": {
    "Amc": null,
    "Snu": "후두근육의 국소성 근긴장이상으로 인하여 발생하는 발성장애이다.",
    "Kdca": null,
    "Final": null,
    "1200": null
  },
  "원인": {
    "Amc": null,
    "Snu": "발성 중 발생하는 후두근육의 불수의적이고 비정상적인 근육의 수축이 원인이다.",
    "Kdca": null,
    "Final": null,
    "1200": null
  },
  "진단": {
    "Amc": null,
    "Snu": null,
    "Kdca": null,
    "Final": null,
    "1200": null
  },
  "치료": {
    "Amc": null,
    "Snu": "1. 보툴리눔톡신 치료: 보툴리눔독소는 신경근접합부에서 아세틸콜린의 분비를 억제하는 작용을 하여 근육의 활성도를 감소시킨다. 2. 수술적 치료: 후두근육 수축을 제어하기 위해 반회후두신경절제술, 갑상연골성형술, 갑상피열근 부분적인 근절제술,  신경제거술, 신경재식술 등 다양한 방법의 수술들이 소개되고 시행되고 있으나 보툴리눔독소의 주입술이 일차적으로 시행되며 수술은 제한된 환자를 대상으로 선택적으로 시행되고 있다.",
    "Kdca": null,
    "Final": null,
    "1200": null
  },
  "진료과": {
    "Amc": null,
    "Snu": "이비인후과",
    "Kdca": null,
    "Final": null,
    "1200": null
  }
}