{
  "병명": "임균 감염증",
  "증상": {
    "Amc": null,
    "Snu": "남성의 경우 전립선염 , 고환-부고환염 등을 일으킬 수 있고 가장 흔하게 발생하는 것은 급성 요도염 으로 이 경우 임균에 감염된 지 2~7일 정도 후에 배뇨통 을 동반한 농성(고름 성분) 분비물이 요도를 통해 배출된다. 여성의 경우 골반 내 염증을 일으키며, 임균 감염 후 대체로 10일 내에 자궁경부염 의 형태로 나타난다. 질을 통해 농성 분비물이 배출되고 요도염이 동반되었을 경우에는 배뇨통, 빈뇨, 긴박뇨(소변을 보고 싶은 마음이 긴박하게 들면서 소변을 보러 가는 도중 배뇨를 함)가 나타날 수 있다. 여성의 임균 감염증은 남성보다 증상의 강도가 약하거나 무증상인 경우도 있다. 여성과 남성 동성애자의 경우 인두염, 직장염이 발생할 수 있으며 균의 침범부위에 따른 증상이 나타난다. 결막염 은 주로 임질에 감염된 여성에게서 자연분만으로 태어난 신생아에서 발생하며 드물게 성인에서도 발생한다. 적절하게 치료하지 않으면 실명할 수 있다.",
    "Kdca": null,
    "Final": null,
    "1200": null
  },
  "정의": {
    "Amc": null,
    "Snu": "임균 감염증(임질)은 성관계를 통해 임균에 감염되어 발생하는 남성 또는 여성 생식기의 감염증이다. 성행위를 통해 감염된 임균은 남성과 여성 비뇨생식기에 염증을 일으킨다. 남성과 여성은 다소 다른 증상과 경과를 나타난다. 임균",
    "Kdca": null,
    "Final": null,
    "1200": null
  },
  "원인": {
    "Amc": null,
    "Snu": "임균 감염증은 임균(Neisseria gonorrhea)의 감염에 의해 발생하며 성관계를 통하여 전파된다. 따라서 성관계가 활발한 젊은 연령층에서 잘 발생한다. 소아가 임균 감염증에 걸리면 성적 학대의 가능성을 고려해 보아야 한다.",
    "Kdca": null,
    "Final": null,
    "1200": null
  },
  "진단": {
    "Amc": null,
    "Snu": null,
    "Kdca": null,
    "Final": null,
    "1200": null
  },
  "치료": {
    "Amc": null,
    "Snu": "임균 감염증 치료에는 항생제 치료가 필요하다. 세프트리악손(ceftriaxone) 근육 주사, 세픽심(cefixime) 경구 복용, 그 외에 퀴놀론(quinolone)계열 항생제를 투여한다. 클라디미디아 감염증의 가능성이 배제되지 않으면 아지스로마이신(azithromycin)이나 독시사이클린(doxycycline)을 같이 투여한다. 여성의 임균 감염에서 골반 내 염증으로 고열, 심한 복통 등의 증상이 동반되는 경우 입원하여 항생제 주사 투약이 필요한 경우도 있다. 임질에 감염된 사람은 처음 보균자와 접촉한 시점부터 치료가 완전히 끝날 때까지 다른 사람에게 전염시킬 가능성이 있기 때문에 성관계 파트너도 함께 치료해야 한다.",
    "Kdca": null,
    "Final": null,
    "1200": null
  },
  "진료과": {
    "Amc": null,
    "Snu": "감염내과, 산부인과",
    "Kdca": null,
    "Final": null,
    "1200": null
  }
}