{
  "병명": "자반",
  "증상": {
    "Amc": null,
    "Snu": "다양한 크기의 자반이 생긴다.",
    "Kdca": null,
    "Final": null,
    "1200": null
  },
  "정의": {
    "Amc": null,
    "Snu": "자반은 진피층으로 적혈구의 유출이 발생하여 피부가 붉은색이나 보라색으로 변색되어 해당 부위를 압박하여도 색이 변하지 않는 상태를 말한다. 자반과 점상 출혈은 같은 병변이며 크기에 따라서 직경이 3㎜ 이상이면 자반, 3㎜ 미만을 점상 출혈이라고 부른다. 구진성 홍반을 보이는 경우, 즉 자반이 생긴 피부가 주위보다 솟아오른 경우 촉지 자반이라고 하며 이는 혈관에 염증이 있음을 말해준다.",
    "Kdca": null,
    "Final": null,
    "1200": null
  },
  "원인": {
    "Amc": null,
    "Snu": "자반증의 원인은 매우 다양한데, 혈소판장애, 혈액응고장애 가 흔하나, 혈관벽의 염증 및 결체조직질환등이 원인이 되기도 한다. 그 외에 패혈증 이나, 면역질환등이 원인이 되는 경우도 있다.",
    "Kdca": null,
    "Final": null,
    "1200": null
  },
  "진단": {
    "Amc": null,
    "Snu": null,
    "Kdca": null,
    "Final": null,
    "1200": null
  },
  "치료": {
    "Amc": null,
    "Snu": "자반은 적혈구가 혈관 밖으로 유출되어 생기는 증상으로 그 자체는 대부분 수주 정도가 지나면 자연적으로 사라진다. 하지만 자반이 생기면 그와 연관된 전신 질환이 있는지를 확인해야 한다. 자반은 대부분 아무런 흔적 없이 사라지지만 혈관 이상이 동반된 자반은 오래 지속되거나 평생 남아있을 수도 있다. 염증 후 색소침착이 남거나 흉터가 남는 소수의 경우에서 색소 레이저 및 혈관 레이저 등의 치료를 시행하기도 한다.",
    "Kdca": null,
    "Final": null,
    "1200": null
  },
  "진료과": {
    "Amc": null,
    "Snu": "혈액종양내과",
    "Kdca": null,
    "Final": null,
    "1200": null
  }
}